pigreads/.gitignore
pigreads/__init__.py
pigreads/_version.py
pigreads/_version.pyi
pigreads/cli.py
pigreads/compat.py
pigreads/core.py
pigreads/diffusivity.py
pigreads/gui.py
pigreads/helper.py
pigreads/kernels.py
pigreads/models.py
pigreads/plot.py
pigreads/progress.py
pigreads/py.typed
pigreads/schema/__init__.py
pigreads/schema/basic.py
pigreads/schema/diffusivity.py
pigreads/schema/model.py
pigreads/schema/setter.py
pigreads/schema/simulation.py
pigreads/schema/stimulus.py
pigreads-0.5.1.dist-info/licenses/LICENSE
pigreads-0.5.1.dist-info/METADATA
pigreads-0.5.1.dist-info/WHEEL
pigreads-0.5.1.dist-info/entry_points.txt
pigreads-0.5.1.dist-info/top_level.txt
pigreads-0.5.1.dist-info/RECORD
