Metadata-Version: 2.4
Name: pigreads
Version: 0.5.1
Summary: Python-integrated GPU-enabled reaction-diffusion solver
Author-email: Desmond Kabus <desmond@kabus.eu>
Project-URL: Homepage, https://gitlab.com/pigreads/pigreads
Project-URL: Documentation, https://pigreads.readthedocs.io
Project-URL: Bug Tracker, https://gitlab.com/pigreads/pigreads/-/issues
Project-URL: Discussions, https://gitlab.com/pigreads/pigreads/-/issues
Project-URL: Changelog, https://gitlab.com/pigreads/pigreads/-/releases
Classifier: Development Status :: 4 - Beta
Classifier: Environment :: GPU
Classifier: Intended Audience :: Science/Research
Classifier: Intended Audience :: Developers
Classifier: License :: OSI Approved :: MIT License
Classifier: Operating System :: OS Independent
Classifier: Programming Language :: Python
Classifier: Programming Language :: Python :: 3
Classifier: Programming Language :: Python :: 3 :: Only
Classifier: Programming Language :: Python :: 3.10
Classifier: Programming Language :: Python :: 3.11
Classifier: Programming Language :: Python :: 3.12
Classifier: Programming Language :: Python :: 3.13
Classifier: Programming Language :: C
Classifier: Programming Language :: C++
Classifier: Topic :: Scientific/Engineering
Classifier: Topic :: Scientific/Engineering :: Physics
Classifier: Topic :: Scientific/Engineering :: Bio-Informatics
Classifier: Typing :: Typed
Requires-Python: >=3.10
License-File: LICENSE
Requires-Dist: numpy>=2.0
Requires-Dist: pyyaml>=6.0
Requires-Dist: pydantic>=2.10
Requires-Dist: pyopencl>=2025.2.6
Requires-Dist: jinja2>=3.1.6
Provides-Extra: plot
Requires-Dist: matplotlib>=3.10; extra == "plot"
Requires-Dist: tqdm>=4.67; extra == "plot"
Provides-Extra: cli
Requires-Dist: pigreads[plot]; extra == "cli"
Requires-Dist: click>=8.1; extra == "cli"
Provides-Extra: gui
Requires-Dist: pigreads[cli]; extra == "gui"
Requires-Dist: pygame>=2.6.1; extra == "gui"
Provides-Extra: colormaps
Requires-Dist: cmcrameri>=1.9; extra == "colormaps"
Provides-Extra: all
Requires-Dist: pigreads[colormaps]; extra == "all"
Requires-Dist: pigreads[gui]; extra == "all"
Provides-Extra: test
Requires-Dist: pigreads[all]; extra == "test"
Requires-Dist: pytest>=6; extra == "test"
Requires-Dist: pytest-cov>=3; extra == "test"
Provides-Extra: dev
Requires-Dist: pigreads[test]; extra == "dev"
Requires-Dist: jinja2>=3; extra == "dev"
Requires-Dist: myokit>=1.37; extra == "dev"
Provides-Extra: docs
Requires-Dist: pigreads[all]; extra == "docs"
Requires-Dist: sphinx>=7.0; extra == "docs"
Requires-Dist: myst_parser>=0.13; extra == "docs"
Requires-Dist: sphinx_copybutton>=0.5.2; extra == "docs"
Requires-Dist: sphinx_autodoc_typehints>=3.5; extra == "docs"
Requires-Dist: autodoc_pydantic>=2.2; extra == "docs"
Requires-Dist: sphinx-click>=6.0.0; extra == "docs"
Requires-Dist: sphinx_lfs_content>=1.1; extra == "docs"
Requires-Dist: furo>=2023.08.17; extra == "docs"
Dynamic: license-file
